wordpress_toolbox/__init__.py
wordpress_toolbox/exceptions.py
wordpress_toolbox/settings.py
wordpress_toolbox/cli/__init__.py
wordpress_toolbox/cli/add_post.py
wordpress_toolbox/cli/authenticate.py
wordpress_toolbox/cli/create_post.py
wordpress_toolbox/cli/get_post.py
wordpress_toolbox/cli/get_posts.py
wordpress_toolbox/cli/options.py
wordpress_toolbox/utils/__init__.py
wordpress_toolbox/utils/create_post_content.py
wordpress_toolbox/utils/format_as_html.py
wordpress_toolbox/utils/get_authentication_header.py
wordpress_toolbox/utils/get_footer_html.py
wordpress_toolbox/utils/get_form_html.py
wordpress_toolbox/utils/get_header_html.py
wordpress_toolbox/utils/get_jwt.py
wordpress_toolbox/utils/get_post_content.py
wordpress_toolbox/utils/get_tag_html.py
wordpress_toolbox/utils/make_request.py
wordpress_toolbox/utils/make_url.py
wordpress_toolbox/utils/read_credentials.py
wordpress_toolbox/utils/read_jwt.py
wordpress_toolbox/utils/save_credentials.py
wordpress_toolbox/utils/save_jwt.py
wordpress_toolbox-0.1.2.dist-info/LICENSE.txt
wordpress_toolbox-0.1.2.dist-info/METADATA
wordpress_toolbox-0.1.2.dist-info/WHEEL
wordpress_toolbox-0.1.2.dist-info/entry_points.txt
wordpress_toolbox-0.1.2.dist-info/top_level.txt
wordpress_toolbox-0.1.2.dist-info/RECORD
