Metadata-Version: 2.1
Name: wordpress-toolbox
Version: 0.1.2
Summary: A collection of CLI commands to use for a wordpress website through it's REST API
Home-page: https://github.com/alexseitsinger/wordpress_toolbox
Author: Alex Seitsinger
Author-email: contact@alexseitsinger.com
License: BSD 2-Clause License
Platform: UNKNOWN
Classifier: Programming Language :: Python :: 3
Classifier: License :: OSI Approved :: BSD License
Requires-Dist: requests
Requires-Dist: click
Requires-Dist: python-slugify
